scibiomart/__init__.py
scibiomart/__main__.py
scibiomart/annot.py
scibiomart/api.py
scibiomart/base.py
scibiomart/errors.py
scibiomart/main.py
scibiomart/scibiomart.py
scibiomart-1.0.2.data/data/LICENSE
scibiomart-1.0.2.dist-info/LICENSE
scibiomart-1.0.2.dist-info/METADATA
scibiomart-1.0.2.dist-info/WHEEL
scibiomart-1.0.2.dist-info/entry_points.txt
scibiomart-1.0.2.dist-info/top_level.txt
scibiomart-1.0.2.dist-info/RECORD
