Metadata-Version: 2.1
Name: scibiomart
Version: 1.0.2
Summary: UNKNOWN
Home-page: https://github.com/ArianeMora/scibiomart
Author: Ariane Mora
Author-email: ariane.n.mora@gmail.com
License: GPL3
Project-URL: Bug Tracker, https://github.com/ArianeMora/scibiomart/issues
Project-URL: Documentation, https://github.com/ArianeMora/scibiomart
Project-URL: Source Code, https://github.com/ArianeMora/scibiomart
Keywords: biomart
Platform: UNKNOWN
Classifier: Development Status :: 5 - Production/Stable
Classifier: Intended Audience :: Science/Research
Classifier: License :: OSI Approved :: GNU General Public License v3 (GPLv3)
Classifier: Natural Language :: English
Classifier: Operating System :: OS Independent
Classifier: Programming Language :: Python :: 3.6
Classifier: Programming Language :: Python :: 3.7
Classifier: Programming Language :: Python :: 3.8
Classifier: Topic :: Scientific/Engineering :: Bio-Informatics
Requires-Python: >=3.6
Requires-Dist: pandas
Requires-Dist: numpy
Requires-Dist: sciutil
Requires-Dist: xmltodict
Requires-Dist: urllib3
